accuralai_core/__init__.py
accuralai_core/cli/__init__.py
accuralai_core/cli/interactive.py
accuralai_core/cli/main.py
accuralai_core/cli/output.py
accuralai_core/cli/state.py
accuralai_core/cli/commands/generate.py
accuralai_core/cli/tools/models.py
accuralai_core/cli/tools/registry.py
accuralai_core/cli/tools/runner.py
accuralai_core/cli/tools/builtin/__init__.py
accuralai_core/cli/tools/builtin/change_working_directory.py
accuralai_core/cli/tools/builtin/copy_file.py
accuralai_core/cli/tools/builtin/create_directory.py
accuralai_core/cli/tools/builtin/delete_file.py
accuralai_core/cli/tools/builtin/file_info.py
accuralai_core/cli/tools/builtin/get_environment_variables.py
accuralai_core/cli/tools/builtin/get_working_directory.py
accuralai_core/cli/tools/builtin/grep_text.py
accuralai_core/cli/tools/builtin/history_export.py
accuralai_core/cli/tools/builtin/list_directory.py
accuralai_core/cli/tools/builtin/move_file.py
accuralai_core/cli/tools/builtin/path_exists.py
accuralai_core/cli/tools/builtin/read_file.py
accuralai_core/cli/tools/builtin/run_command.py
accuralai_core/cli/tools/builtin/search_files.py
accuralai_core/cli/tools/builtin/session_info.py
accuralai_core/cli/tools/builtin/write_file.py
accuralai_core/config/__init__.py
accuralai_core/config/defaults.py
accuralai_core/config/loader.py
accuralai_core/config/schema.py
accuralai_core/connectors/__init__.py
accuralai_core/connectors/backend.py
accuralai_core/connectors/cache.py
accuralai_core/connectors/canonicalize.py
accuralai_core/connectors/post_process.py
accuralai_core/connectors/router.py
accuralai_core/connectors/validator.py
accuralai_core/contracts/__init__.py
accuralai_core/contracts/errors.py
accuralai_core/contracts/models.py
accuralai_core/contracts/protocols.py
accuralai_core/core/__init__.py
accuralai_core/core/context.py
accuralai_core/core/events.py
accuralai_core/core/instrumentation.py
accuralai_core/core/lifecycle.py
accuralai_core/core/orchestrator.py
accuralai_core-0.2.1.dist-info/METADATA
accuralai_core-0.2.1.dist-info/WHEEL
accuralai_core-0.2.1.dist-info/entry_points.txt
accuralai_core-0.2.1.dist-info/licenses/LICENSE
accuralai_core-0.2.1.dist-info/RECORD
