Metadata-Version: 2.4
Name: accuralai-core
Version: 0.2.1
Summary: Async orchestration nucleus for the AccuralAI local LLM ecosystem.
Project-URL: homepage, https://accural-ai.web.app/
Project-URL: repository, https://github.com/accuralai/accuralai-core
Project-URL: documentation, https://accuralai.readthedocs.io/en/latest/packages/accuralai-core/index.html
Author: AccuralAI Maintainers
License: Apache-2.0
License-File: LICENSE
Requires-Python: >=3.10
Requires-Dist: anyio>=3.7
Requires-Dist: click>=8.1
Requires-Dist: pydantic-settings>=2.2
Requires-Dist: pydantic>=2.5
Requires-Dist: tomli>=2.0; python_version < '3.11'
Requires-Dist: typing-extensions>=4.7
Provides-Extra: all-backends
Requires-Dist: accuralai-google; extra == 'all-backends'
Requires-Dist: accuralai-ollama; extra == 'all-backends'
Provides-Extra: all-plugins
Requires-Dist: accuralai-cache; extra == 'all-plugins'
Requires-Dist: accuralai-canonicalize; extra == 'all-plugins'
Requires-Dist: accuralai-router; extra == 'all-plugins'
Requires-Dist: accuralai-validator; extra == 'all-plugins'
Provides-Extra: cache
Requires-Dist: accuralai-cache; extra == 'cache'
Provides-Extra: canonicalize
Requires-Dist: accuralai-canonicalize; extra == 'canonicalize'
Provides-Extra: cli
Requires-Dist: accuralai-cli; extra == 'cli'
Provides-Extra: complete
Requires-Dist: accuralai-cache; extra == 'complete'
Requires-Dist: accuralai-canonicalize; extra == 'complete'
Requires-Dist: accuralai-google; extra == 'complete'
Requires-Dist: accuralai-ollama; extra == 'complete'
Requires-Dist: accuralai-rag; extra == 'complete'
Requires-Dist: accuralai-router; extra == 'complete'
Requires-Dist: accuralai-validator; extra == 'complete'
Provides-Extra: dev
Requires-Dist: pytest; extra == 'dev'
Requires-Dist: pytest-anyio; extra == 'dev'
Requires-Dist: pytest-mock; extra == 'dev'
Requires-Dist: ruff; extra == 'dev'
Provides-Extra: google
Requires-Dist: accuralai-google; extra == 'google'
Provides-Extra: ollama
Requires-Dist: accuralai-ollama; extra == 'ollama'
Provides-Extra: rag
Requires-Dist: accuralai-rag; extra == 'rag'
Provides-Extra: router
Requires-Dist: accuralai-router; extra == 'router'
Provides-Extra: validators
Requires-Dist: accuralai-validator; extra == 'validators'
